{"id":37,"slug":"37-8th-edition-booster-box","name":"Booster Box","image":"https://static.mtgstocks.com/sealedimage/t37.png","tcgUrl":"https://www.tcgplayer.com/product/27259/magic-8th-edition-8th-edition-booster-box","set":{"id":67,"name":"8th Edition","abbreviation":"8ED","icon_class":"ss-8ed","slug":"67-8th-edition"},"allTimeHigh":{"average":2505.49,"date":1628553600000},"allTimeLow":{"average":1854.99,"date":1627257600000},"latestPrice":{"low":1860.01,"average":2200,"high":2499.99,"market":null},"cardkingdom":{"priceRetail":999.99,"url":"https://www.cardkingdom.com/mtg-sealed/8th-edition-booster-box?partner=mtgstocks&utm_source=mtgstocks&utm_medium=affiliate&utm_campaign=mtgstocks&partner_args=sealed_37"},"differences":{"yesterday":{"average":0,"market":null},"lastWeek":{"average":0.1,"market":null},"lastMonth":{"average":0,"market":null}}}